topsispck/__init__.py
topsispck/topsis.py
topsis_101703385-0.0.1.dist-info/LICENCE.txt
topsis_101703385-0.0.1.dist-info/METADATA
topsis_101703385-0.0.1.dist-info/WHEEL
topsis_101703385-0.0.1.dist-info/top_level.txt
topsis_101703385-0.0.1.dist-info/RECORD
